InsufficientGibbs/Distribution.py
InsufficientGibbs/Model.py
InsufficientGibbs/Models.py
InsufficientGibbs/Variable.py
InsufficientGibbs/__init__.py
InsufficientGibbs-1.2.1.dist-info/LICENSE.txt
InsufficientGibbs-1.2.1.dist-info/METADATA
InsufficientGibbs-1.2.1.dist-info/WHEEL
InsufficientGibbs-1.2.1.dist-info/entry_points.txt
InsufficientGibbs-1.2.1.dist-info/top_level.txt
InsufficientGibbs-1.2.1.dist-info/RECORD
