Metadata-Version: 2.1
Name: InsufficientGibbs
Version: 1.2.1
Summary: Package for performing Bayesian inference with insufficient and robust statistics.
Home-page: https://github.com/AntoineLuciano/Insufficient-Gibbs-Sampling
Project-URL: Changelog, https://github.com/AntoineLuciano/Insufficient-Gibbs-Sampling/releases
Classifier: Programming Language :: Python :: 3
Classifier: License :: OSI Approved :: MIT License
Classifier: Intended Audience :: Developers
Requires-Python: >=3.6
License-File: LICENSE.txt
